fortunes/__init__.py
fortunes/getMultipleFortunes.py
fortunes/get_quotes_by_author.py
fortunes/random_fortune.py
fortunes/send_email.py
fortune_package-0.1.5.dist-info/LICENSE
fortune_package-0.1.5.dist-info/METADATA
fortune_package-0.1.5.dist-info/WHEEL
fortune_package-0.1.5.dist-info/top_level.txt
fortune_package-0.1.5.dist-info/RECORD
