Metadata-Version: 2.1
Name: fortune_package
Version: 0.1.5
Summary: A funny fortunes generator package
Author-email: Yuhao Sheng <ys4689@nyu.edu>, Ryoma Nagano <rn2247@nyu.edu>, Qiyuan Yin <qy765@nyu.edu>, Andrea Tang <xt2073@nyu.edu>
License: MIT
License-File: LICENSE
Requires-Dist: python-dotenv
Provides-Extra: dev
Requires-Dist: pytest; extra == "dev"
